{
  "title": "Home",
  "slug": "home",
  "status": "published",
  "seo": {
    "title": "Characom Group — Building Cyprus since 1987",
    "description": "Cypriot construction and development group. Government infrastructure, real estate development and residential communities — built to outlast us, since 1987."
  },
  "sections": [
    {
      "id": "sec-home-hero",
      "type": "hero",
      "props": {
        "kicker": "CHARACOM GROUP — BUILDING CYPRUS SINCE 1987",
        "headline": "We build what outlasts us.",
        "subheadline": "Government infrastructure, real estate and residential craft — delivered across Cyprus by one accountable team.",
        "buttons": [
          {
            "label": "Explore Portfolio",
            "href": "/portfolio",
            "variant": "gold",
            "newTab": false
          },
          {
            "label": "Get in Touch",
            "href": "/contact",
            "variant": "ghost",
            "newTab": false
          }
        ],
        "media": {
          "mode": "image",
          "videoSrc": "",
          "posterSrc": "",
          "image": {
            "src": "https://images.unsplash.com/photo-1541888946425-d81bb19240f5?q=80&w=2400&auto=format&fit=crop",
            "alt": "Construction site at dusk with tower cranes over Cyprus"
          }
        },
        "showScrollCue": true
      },
      "visible": true
    },
    {
      "id": "sec-home-stats",
      "type": "statsCounters",
      "props": {
        "kicker": "The record",
        "heading": "",
        "useSiteStats": true,
        "items": [],
        "dark": true
      },
      "visible": true
    },
    {
      "id": "sec-home-group",
      "type": "imageWithText",
      "props": {
        "kicker": "The Group",
        "heading": "Four decades of building Cyprus",
        "body": "Characom Group began in 1987 as a two-crew contractor pouring foundations on the edge of Nicosia. Four decades later, the same discipline runs through everything we deliver — from motorway interchanges to seafront homes.\n\nWe keep development, engineering and construction under one roof. It is a slower way to build a company, and it is why clients return: a single team stays accountable from first survey to final handover.\n\nToday more than 650 engineers, builders and craftspeople carry the group's standard across the island — build it once, build it right, build it to outlast us.",
        "image": {
          "src": "https://images.unsplash.com/photo-1518005020951-eccb494ad742?q=80&w=1920&auto=format&fit=crop",
          "alt": "Modern concrete building rising against the sky"
        },
        "imageSide": "right",
        "link": {
          "label": "More about us",
          "href": "/about",
          "variant": "text",
          "newTab": false
        },
        "dark": false
      },
      "visible": true
    },
    {
      "id": "sec-scene-mansion",
      "type": "constructionScene",
      "props": {
        "kicker": "How we build",
        "heading": "A home, from the ground up",
        "text": "One scroll through a Characom build: the crew arrives, the villa rises, the gardens grow, and a family moves in.",
        "variant": "mansion",
        "floors": 12,
        "caption": "Scroll to build",
        "reasons": [
          {
            "title": "Cypriot and family owned",
            "text": "Three generations of one family, building on the island we call home since 1987."
          },
          {
            "title": "Deep partner ties",
            "text": "Suppliers, banks and municipalities that have worked with us for decades."
          },
          {
            "title": "Locally known, locally trusted",
            "text": "Walk any Cypriot town and you will pass a Characom build within minutes."
          },
          {
            "title": "Here long after handover",
            "text": "Our aftercare teams live in the communities we build."
          }
        ]
      },
      "visible": true
    },
    {
      "id": "sec-home-sectors",
      "type": "sectorCards",
      "props": {
        "kicker": "What we do",
        "heading": "Three sectors, one standard",
        "useCategories": true,
        "cards": []
      },
      "visible": true
    },
    {
      "id": "sec-scene-tower",
      "type": "constructionScene",
      "props": {
        "kicker": "Twelve floors, twelve reasons",
        "heading": "Why Cyprus builds with us",
        "text": "",
        "variant": "tower",
        "floors": 12,
        "caption": "Scroll to raise the tower",
        "reasons": [
          {
            "title": "Best and safest materials only",
            "text": "Every structural element is certified, traceable and tested before it reaches the site."
          },
          {
            "title": "Delivery on programme, every time",
            "text": "Four decades without a missed government handover date."
          },
          {
            "title": "One accountable team",
            "text": "Survey, engineering, construction and handover under a single roof."
          },
          {
            "title": "In-house engineering and QA",
            "text": "Our own engineers check every level before the next one rises."
          },
          {
            "title": "Government-grade compliance",
            "text": "The same tender-level controls apply to every private home we build."
          },
          {
            "title": "Transparent costs",
            "text": "Open-book budgets with no hidden extras, ever."
          },
          {
            "title": "An industry-leading safety record",
            "text": "Over 1,200 lost-time-incident-free days and counting."
          },
          {
            "title": "Craftsmen who stay",
            "text": "Site teams that have built with us for decades, not seasons."
          },
          {
            "title": "Energy-smart designs",
            "text": "Buildings engineered to cut running costs from day one."
          },
          {
            "title": "Local supply chains",
            "text": "Cypriot materials and partners mean faster lead times."
          },
          {
            "title": "A ten-year structural warranty",
            "text": "Standard on everything we hand over."
          },
          {
            "title": "Care that outlasts handover",
            "text": "Aftercare teams stay on call long after the keys change hands."
          }
        ]
      },
      "visible": true
    },
    {
      "id": "sec-home-featured",
      "type": "featuredProjects",
      "props": {
        "kicker": "Selected work",
        "heading": "Featured projects",
        "limit": 5
      },
      "visible": true
    },
    {
      "id": "sec-home-timeline",
      "type": "timeline",
      "props": {
        "kicker": "Since 1987",
        "heading": "Four decades of building",
        "milestones": [
          {
            "year": "1987",
            "title": "Founded in Nicosia",
            "text": "Andreas Characos registers the firm with two crews, one mixer truck and a ledger he still keeps."
          },
          {
            "year": "1999",
            "title": "First government contract",
            "text": "A district school extension in Larnaca opens the group's public-works record — 85 contracts and counting."
          },
          {
            "year": "2011",
            "title": "500th home delivered",
            "text": "The Elaia courtyard scheme marks half a thousand Cypriot families housed by the group."
          },
          {
            "year": "2024",
            "title": "1.2 million sq.m",
            "text": "Cumulative developed area passes 1.2 million square metres across all three sectors."
          }
        ],
        "compact": true,
        "link": {
          "label": "Our story",
          "href": "/about",
          "variant": "text",
          "newTab": false
        }
      },
      "visible": true
    },
    {
      "id": "sec-home-news",
      "type": "newsList",
      "props": {
        "kicker": "Newsroom",
        "heading": "Latest news",
        "limit": 3,
        "showAllLink": true
      },
      "visible": true
    },
    {
      "id": "sec-home-cta",
      "type": "ctaBand",
      "props": {
        "kicker": "Next",
        "heading": "Have a project in mind?",
        "text": "Tell us what you are planning — an engineer replies within two working days.",
        "button": {
          "label": "Get in touch",
          "href": "/contact",
          "variant": "gold",
          "newTab": false
        }
      },
      "visible": true
    }
  ],
  "draftSections": null,
  "updatedAt": "2026-07-07T12:00:00.000Z"
}
